{"errors":[],"warnings":[],"namedChunkGroups":{"polyfill":{"chunks":[3,0,8],"assets":["webpack-runtime-a4a3adf158d2a16087aa.js","webpack-runtime-a4a3adf158d2a16087aa.js.map","commons-abb22ca1ff0887d8d68e.js","commons-abb22ca1ff0887d8d68e.js.map","polyfill-b3cdf4efa4860a9f5b07.js","polyfill-b3cdf4efa4860a9f5b07.js.map"],"children":{},"childAssets":{}},"app":{"chunks":[3,7,0,4],"assets":["webpack-runtime-a4a3adf158d2a16087aa.js","webpack-runtime-a4a3adf158d2a16087aa.js.map","framework-83e11af5cf111be5ad89.js","framework-83e11af5cf111be5ad89.js.map","commons-abb22ca1ff0887d8d68e.js","commons-abb22ca1ff0887d8d68e.js.map","app-52261a8d516359759ca9.js","app-52261a8d516359759ca9.js.map"],"children":{},"childAssets":{}},"component---src-pages-404-js":{"chunks":[2,1,0,5],"assets":["cb1608f2-eca9cad0c0c5cdca01cb.js","cb1608f2-eca9cad0c0c5cdca01cb.js.map","a9a7754c-e76acebf64011c120699.js","a9a7754c-e76acebf64011c120699.js.map","commons-abb22ca1ff0887d8d68e.js","commons-abb22ca1ff0887d8d68e.js.map","component---src-pages-404-js-3f2d916b8de46d89013f.js","component---src-pages-404-js-3f2d916b8de46d89013f.js.map"],"children":{},"childAssets":{}},"component---src-pages-index-js":{"chunks":[2,1,0,6],"assets":["cb1608f2-eca9cad0c0c5cdca01cb.js","cb1608f2-eca9cad0c0c5cdca01cb.js.map","a9a7754c-e76acebf64011c120699.js","a9a7754c-e76acebf64011c120699.js.map","commons-abb22ca1ff0887d8d68e.js","commons-abb22ca1ff0887d8d68e.js.map","component---src-pages-index-js-9d9e3694f2794ebf77ed.js","component---src-pages-index-js-9d9e3694f2794ebf77ed.js.map"],"children":{},"childAssets":{}}},"assetsByChunkName":{"polyfill":["webpack-runtime-a4a3adf158d2a16087aa.js","commons-abb22ca1ff0887d8d68e.js","polyfill-b3cdf4efa4860a9f5b07.js"],"app":["webpack-runtime-a4a3adf158d2a16087aa.js","framework-83e11af5cf111be5ad89.js","commons-abb22ca1ff0887d8d68e.js","app-52261a8d516359759ca9.js"],"component---src-pages-404-js":["cb1608f2-eca9cad0c0c5cdca01cb.js","a9a7754c-e76acebf64011c120699.js","commons-abb22ca1ff0887d8d68e.js","component---src-pages-404-js-3f2d916b8de46d89013f.js"],"component---src-pages-index-js":["cb1608f2-eca9cad0c0c5cdca01cb.js","a9a7754c-e76acebf64011c120699.js","commons-abb22ca1ff0887d8d68e.js","component---src-pages-index-js-9d9e3694f2794ebf77ed.js"]}}